xontrib/hist_navigator.py
xontrib_hist_navigator-0.6.5.dist-info/WHEEL
xontrib_hist_navigator-0.6.5.dist-info/METADATA
xontrib_hist_navigator-0.6.5.dist-info/licenses/LICENSE
xontrib_hist_navigator-0.6.5.dist-info/RECORD
