Metadata-Version: 2.1
Name: xontrib-hist-navigator
Version: 0.6.5
Summary: A Xonsh plugin to navigate between directories like fish's prevd/nextd
License: MIT
Keywords: xontrib,xonsh
Author-email: Noortheen Raja <jnoortheen@gmail.com>
Requires-Python: >=3.7
Classifier: Intended Audience :: Developers
Classifier: License :: OSI Approved :: MIT License
Classifier: Natural Language :: English
Classifier: Operating System :: OS Independent
Classifier: Programming Language :: Python
Classifier: Programming Language :: Python :: 3
Classifier: Programming Language :: Python :: 3.6
Classifier: Programming Language :: Python :: 3.7
Classifier: Programming Language :: Python :: 3.8
Classifier: Topic :: Software Development
Classifier: Topic :: System :: Shells
Classifier: Topic :: System :: System Shells
Classifier: Topic :: Terminals
Classifier: Topic :: Utilities
Requires-Dist: prompt-toolkit
Requires-Dist: xonsh>=0.11
Provides-Extra: dev
Requires-Dist: pytest; extra == "dev"
Requires-Dist: black; extra == "dev"
Requires-Dist: build>=0.10.0; extra == "dev"
Project-URL: homepage, https://pypi.org/project/xontrib-hist-navigator
Project-URL: repository, https://github.com/jnoortheen/xontrib-hist-navigator
